sosimpy/__init__.py
sosimpy/analysis/__init__.py
sosimpy/analysis/clean_agentlogdb.py
sosimpy/analysis/generate_vizualizaiton.py
sosimpy/analysis/grab_data.py
sosimpy/analysis/heatmap.png
sosimpy/analysis/score_distribution_gif.py
sosimpy/analysis/uniform_sample_agents.py
sosimpy/analysis/visualize_simulation.py
sosimpy/analysis/vizualizations.py
sosimpy/config/__init__.py
sosimpy/config/config.py
sosimpy/config/questionnaire_questions.py
sosimpy/config/starter_prompts.py
sosimpy/preprocessing/pdf2sim.py
sosimpy/simulation/__init__.py
sosimpy/simulation/agents/__init__.py
sosimpy/simulation/agents/agent.py
sosimpy/simulation/agents/agentProperty.py
sosimpy/simulation/agents/generate_questionnaire_answer.py
sosimpy/simulation/agents/property_updates.py
sosimpy/simulation/conversation/__init__.py
sosimpy/simulation/conversation/assign_pairs.py
sosimpy/simulation/conversation/conversation.py
sosimpy/simulation/conversation/conversation_memory.py
sosimpy/simulation/conversationSelector/BaseSelectionLogic.py
sosimpy/simulation/conversationSelector/__init__.py
sosimpy/simulation/llmBackBone/__init__.py
sosimpy/simulation/llmBackBone/llm_backbone.py
sosimpy/simulation/logging/__init__.py
sosimpy/simulation/logging/database_manager.py
sosimpy/simulation/logging/log_schemas.py
sosimpy/simulation/logging/utils.py
sosimpy/simulation/metrics/__init__.py
sosimpy/simulation/metrics/metrics.py
sosimpy/simulation/simulationStep/__init__.py
sosimpy/simulation/simulationStep/simulation_step.py
sosimpy/simulation/world.py
sosimpy/vllm_wrapper.py
socsim-0.1.1.dist-info/METADATA
socsim-0.1.1.dist-info/WHEEL
socsim-0.1.1.dist-info/RECORD
